rvtts/__init__.py
rvtts/rvtts.py
rvtts/utils.py
rvtts/version.py
rvtts/tokenizer/__init__.py
rvtts/tokenizer/core.py
rvtts/tokenizer/pre_processors.py
rvtts/tokenizer/symbols.py
rvtts/tokenizer/tokenizer_cases.py
rvtts-1.0.1.dist-info/LICENSE
rvtts-1.0.1.dist-info/METADATA
rvtts-1.0.1.dist-info/WHEEL
rvtts-1.0.1.dist-info/entry_points.txt
rvtts-1.0.1.dist-info/top_level.txt
rvtts-1.0.1.dist-info/RECORD
