Metadata-Version: 2.1
Name: rvtts
Version: 1.0.1
Summary: rvTTS - ResponsiveVoice TTS CLI Tool
Home-page: https://github.com/tinotk/rvtts
Author: Tino Khong
Author-email: tinokhong@gmail.com
License: UNKNOWN
Keywords: rvtts,responsive voice tts,TTS for python3,text to speech for python,tts,text to speech,speech,speech synthesis
Platform: UNKNOWN
Classifier: Programming Language :: Python :: 3
Classifier: License :: OSI Approved :: MIT License
Classifier: Operating System :: OS Independent
Requires-Dist: requests
Requires-Dist: click
Provides-Extra: docs
Requires-Dist: sphinx (>=1.4) ; extra == 'docs'
Requires-Dist: sphinx-rtd-theme ; extra == 'docs'
Requires-Dist: sphinx-click ; extra == 'docs'
